django_command_overrides/__init__.py
django_command_overrides/admin.py
django_command_overrides/apps.py
django_command_overrides/conf/__init__.py
django_command_overrides/conf/app_template/__init__.py-tpl
django_command_overrides/conf/app_template/admin.py-tpl
django_command_overrides/conf/app_template/apps.py-tpl
django_command_overrides/conf/app_template/migrations/__init__.py-tpl
django_command_overrides/conf/app_template/models/__init__.py-tpl
django_command_overrides/conf/app_template/tests/__init__.py-tpl
django_command_overrides/conf/app_template/views/__init__.py-tpl
django_command_overrides/management/__init__.py
django_command_overrides/management/commands/__init__.py
django_command_overrides/management/commands/startapp.py
django_command_overrides/migrations/__init__.py
django_command_overrides-0.1.0.dist-info/LICENSE
django_command_overrides-0.1.0.dist-info/WHEEL
django_command_overrides-0.1.0.dist-info/METADATA
django_command_overrides-0.1.0.dist-info/RECORD
