Metadata-Version: 2.1
Name: django-command-overrides
Version: 0.1.0
Summary: 
Author: Jonathan Meier
Author-email: jonathanwmeier@gmail.com
Requires-Python: >=3.7,<4.0
Classifier: Programming Language :: Python :: 3
Classifier: Programming Language :: Python :: 3.7
Classifier: Programming Language :: Python :: 3.8
Requires-Dist: django (>=2.2)
